.gitattributes
.gitignore
LICENSE
MANIFEST.in
README.rst
requirements.txt
setup.cfg
setup.py
versioneer.py
jsonfiledict/__init__.py
jsonfiledict/_version.py
jsonfiledict/jsonfiledict.py
jsonfiledict.egg-info/PKG-INFO
jsonfiledict.egg-info/SOURCES.txt
jsonfiledict.egg-info/dependency_links.txt
jsonfiledict.egg-info/entry_points.txt
jsonfiledict.egg-info/not-zip-safe
jsonfiledict.egg-info/pbr.json
jsonfiledict.egg-info/requires.txt
jsonfiledict.egg-info/top_level.txt