Metadata-Version: 1.0
Name: jsonfiledict
Version: 0.2.post1
Summary: A dict optionally backed by an auto-updating JSON file.
Home-page: http://kanga.nu/~claw/
Author: J C Lawrence
Author-email: claw@kanga.nu
License: LGPL v3
Platform: UNKNOWN
